{
    "MPN": [
        false,
        "MF-RES-0805-220"
    ],
    "base": "0aaa5955-e860-49fa-9b04-c3fe2d4bc010",
    "datasheet": [
        false,
        "https://s3.amazonaws.com/devpublic1/datasheets/Panasonic_TF_Resistors.pdf"
    ],
    "description": [
        false,
        "Resistor Thick Film 0805 220 Ohm 5% 125mW 150V"
    ],
    "inherit_model": true,
    "inherit_tags": true,
    "manufacturer": [
        true,
        ""
    ],
    "parametric": {
        "pmax": "0.125",
        "table": "resistors",
        "tolerance": "5",
        "value": "220"
    },
    "tags": [],
    "type": "part",
    "uuid": "c09e87c4-807b-56d7-b4fd-e85e832fd57d",
    "value": [
        false,
        "220 Ω"
    ]
}